hashmoji.py
hashmoji-0.1.3.data/scripts/hashmoji.py
hashmoji-0.1.3.dist-info/DESCRIPTION.rst
hashmoji-0.1.3.dist-info/METADATA
hashmoji-0.1.3.dist-info/pydist.json
hashmoji-0.1.3.dist-info/RECORD
hashmoji-0.1.3.dist-info/top_level.txt
hashmoji-0.1.3.dist-info/WHEEL
