Metadata-Version: 2.0
Name: hashmoji
Version: 0.1.3
Summary: Visualize hashes and bytes with emoji.
Home-page: https://github.com/mcroydon/hashmoji
Author: Matt Croydon
Author-email: mcroydon@gmail.com
License: UNKNOWN
Platform: UNKNOWN
Classifier: Development Status :: 3 - Alpha
Classifier: Intended Audience :: Developers
Classifier: License :: OSI Approved :: BSD License
Classifier: Operating System :: OS Independent
Classifier: Operating System :: MacOS :: MacOS X
Classifier: Programming Language :: Python
Classifier: Programming Language :: Python :: 3
